tortoise_api_model/__init__.py
tortoise_api_model/enum.py
tortoise_api_model/field.py
tortoise_api_model/func.py
tortoise_api_model/model.py
tortoise_api_model/pydantic.py
tortoise_api_model-0.10.2.dist-info/METADATA
tortoise_api_model-0.10.2.dist-info/WHEEL
tortoise_api_model-0.10.2.dist-info/top_level.txt
tortoise_api_model-0.10.2.dist-info/RECORD
