Metadata-Version: 2.1
Name: tortoise-api-model
Version: 0.10.2
Summary: Base model for x-api
Author-email: Mike Artemiev <mixartemev@gmail.com>
License: MIT
Project-URL: Homepage, https://github.com/XyncNet/x-model
Project-URL: Repository, https://github.com/XyncNet/x-model
Keywords: tortoise,model,crud,generator,api,admin
Requires-Python: >=3.11
Requires-Dist: tortoise-orm[accel,asyncpg]
Requires-Dist: passlib[bcrypt]
Requires-Dist: pydantic
Requires-Dist: python-dotenv
Provides-Extra: dev
Requires-Dist: pytest ; extra == 'dev'
Requires-Dist: build ; extra == 'dev'
Requires-Dist: twine ; extra == 'dev'
Requires-Dist: setuptools-scm ; extra == 'dev'
